marvin/__init__.py
marvin/api/__init__.py
marvin/api/api.py
marvin/api/base.py
marvin/api/cube.py
marvin/api/general.py
marvin/api/maps.py
marvin/api/modelcube.py
marvin/api/plate.py
marvin/api/query.py
marvin/api/rss.py
marvin/api/spaxel.py
marvin/contrib/__init__.py
marvin/contrib/vacs/__init__.py
marvin/contrib/vacs/base.py
marvin/contrib/vacs/firefly.py
marvin/contrib/vacs/galaxyzoo.py
marvin/contrib/vacs/galaxyzoo3d.py
marvin/contrib/vacs/gema.py
marvin/contrib/vacs/hi.py
marvin/contrib/vacs/visual_morph.py
marvin/core/__init__.py
marvin/core/caching_query.py
marvin/core/exceptions.py
marvin/core/marvin_pickle.py
marvin/data/linearlab.csv
marvin/data/marvin.yml
marvin/data/query_params_best.cfg
marvin/data/query_params_metadata.cfg
marvin/data/sdssMaskbits.par
marvin/db/ArrayUtils.py
marvin/db/DatabaseConnection.py
marvin/db/NumpyAdaptors.py
marvin/db/__init__.py
marvin/db/caching.py
marvin/db/database.py
marvin/db/dbconfig.ini
marvin/db/marvindb.py
marvin/db/models/DapModelClasses.py
marvin/db/models/DataModelClasses.py
marvin/db/models/SampleModelClasses.py
marvin/db/models/__init__.py
marvin/tools/__init__.py
marvin/tools/core.py
marvin/tools/cube.py
marvin/tools/image.py
marvin/tools/maps.py
marvin/tools/modelcube.py
marvin/tools/plate.py
marvin/tools/query.py
marvin/tools/results.py
marvin/tools/rss.py
marvin/tools/sentry.py
marvin/tools/spaxel.py
marvin/tools/vacs.py
marvin/tools/mixins/__init__.py
marvin/tools/mixins/aperture.py
marvin/tools/mixins/caching.py
marvin/tools/mixins/dapall.py
marvin/tools/mixins/mma.py
marvin/tools/mixins/nsa.py
marvin/tools/quantities/__init__.py
marvin/tools/quantities/analysis_props.py
marvin/tools/quantities/base_quantity.py
marvin/tools/quantities/datacube.py
marvin/tools/quantities/map.py
marvin/tools/quantities/spectrum.py
marvin/utils/__init__.py
marvin/utils/yanny.py
marvin/utils/dap/__init__.py
marvin/utils/dap/bpt.py
marvin/utils/datamodel/__init__.py
marvin/utils/datamodel/docudatamodel.py
sdss_marvin-2.8.2.dist-info/LICENSE.md
sdss_marvin-2.8.2.dist-info/METADATA
sdss_marvin-2.8.2.dist-info/WHEEL
sdss_marvin-2.8.2.dist-info/top_level.txt
sdss_marvin-2.8.2.dist-info/RECORD
