Metadata-Version: 2.2
Name: sdss-marvin
Version: 2.8.2
Summary: Toolsuite for dealing with the MaNGA dataset
Home-page: https://github.com/sdss/marvin
Author: The Marvin Developers
Author-email: havok2063@hotmail.com
License: BSD 3-Clause License
Project-URL: Repository, https://github.com/sdss/marvin
Project-URL: Documentation, https://sdss-marvin.readthedocs.org
Keywords: astronomy,software,marvin,manga,MaNGA
Classifier: Development Status :: 4 - Beta
Classifier: Environment :: Web Environment
Classifier: Framework :: Flask
Classifier: Intended Audience :: Science/Research
Classifier: License :: OSI Approved :: BSD License
Classifier: Natural Language :: English
Classifier: Operating System :: OS Independent
Classifier: Programming Language :: Python
Classifier: Programming Language :: Python :: 2.7
Classifier: Programming Language :: Python :: 3.6
Classifier: Programming Language :: Python :: 3.7
Classifier: Topic :: Database :: Front-Ends
Classifier: Topic :: Documentation :: Sphinx
Classifier: Topic :: Internet :: WWW/HTTP :: Dynamic Content
Classifier: Topic :: Scientific/Engineering :: Astronomy
Classifier: Topic :: Software Development :: Libraries :: Python Modules
Classifier: Topic :: Software Development :: User Interfaces
Requires-Python: >=3.8
License-File: LICENSE.md
Requires-Dist: sdsstools>=0.4
Requires-Dist: sdss-tree>=3.1.0
Requires-Dist: sdss-access>=2.0
Requires-Dist: marvin-brain>=0.3
Requires-Dist: marvin-sqlalchemy-boolean-search>=0.2
Requires-Dist: marvin-wtforms-alchemy>=0.18.0
Requires-Dist: astropy>=5.1
Requires-Dist: fuzzywuzzy>=0.15.0
Requires-Dist: python-Levenshtein>=0.12.0
Requires-Dist: raven<7.0,>=5.32.0
Requires-Dist: packaging<21.0,>=20.1
Requires-Dist: yamlordereddictloader>=0.2.2
Requires-Dist: numpy<2.0,>1.20
Requires-Dist: scipy>=0.18.1
Requires-Dist: photutils>=0.7
Requires-Dist: pandas>=1.0
Requires-Dist: matplotlib>=1.5.3
Requires-Dist: webargs<6.0,>=1.5.2
Requires-Dist: werkzeug>=2.0
Requires-Dist: numpyencoder>=0.3
Requires-Dist: dogpile.cache<1.1,>=0.6.2
Provides-Extra: extra
Provides-Extra: dev
Requires-Dist: Sphinx>=3.1.0; extra == "dev"
Requires-Dist: sphinx_bootstrap_theme>=0.4.12; extra == "dev"
Requires-Dist: sphinxcontrib-httpdomain>=1.5.0; extra == "dev"
Requires-Dist: sphinx_issues>=1.0.0; extra == "dev"
Requires-Dist: sphinx-rtd-theme>=0.4.2; extra == "dev"
Requires-Dist: nbsphinx>=0.3.5; extra == "dev"
Requires-Dist: photutils>=0.7; extra == "dev"
Requires-Dist: mpl-scatter-density>=0.4; extra == "dev"
Requires-Dist: jupyter_client>=5.2.3; extra == "dev"
Requires-Dist: ipykernel>5.0; extra == "dev"
Requires-Dist: ipython>=7.9.0; extra == "dev"
Requires-Dist: matplotlib>=3.1.1; extra == "dev"
Requires-Dist: flake8>=3.7.9; extra == "dev"
Requires-Dist: doc8>=0.8.0; extra == "dev"
Requires-Dist: pytest>=7.2.2; extra == "dev"
Requires-Dist: pytest-cov>=2.8.1; extra == "dev"
Requires-Dist: pytest-sugar<1.0.0; extra == "dev"
Requires-Dist: pytest-remotedata>=0.3.2; extra == "dev"
Requires-Dist: pytest-flask>=0.10.0; extra == "dev"
Requires-Dist: pytest-xdist>=1.18.1; extra == "dev"
Requires-Dist: pytest-timeout>=1.2.0; extra == "dev"
Requires-Dist: pytest-mock>=1.13.0; extra == "dev"
Requires-Dist: pytest-split>=0.8; extra == "dev"
Requires-Dist: isort>=4.3.21; extra == "dev"
Requires-Dist: coveralls>=3.0; extra == "dev"
Requires-Dist: codecov>=2.0.15; extra == "dev"
Requires-Dist: coverage[toml]>=5.0; extra == "dev"
Requires-Dist: ipdb>=0.12.3; extra == "dev"
Requires-Dist: invoke>=1.3.0; extra == "dev"
Requires-Dist: twine>=3.1.1; extra == "dev"
Requires-Dist: wheel>=0.33.6; extra == "dev"
Requires-Dist: psycopg2<3.0,>=2.6.2; extra == "dev"
Requires-Dist: selenium>=3.3.1; extra == "dev"
Requires-Dist: page_objects>=1.1.0; extra == "dev"
Requires-Dist: decorator>=4.1.2; extra == "dev"
Requires-Dist: pympler>=0.5; extra == "dev"
Requires-Dist: mpl-scatter-density>=0.4; extra == "dev"
Requires-Dist: msgpack>=0.5.4; extra == "dev"
Requires-Dist: msgpack-numpy>=0.4.2; extra == "dev"
Requires-Dist: Flask-Testing>=0.6.1; extra == "dev"
Provides-Extra: docs
Requires-Dist: Sphinx>=3.1.0; extra == "docs"
Requires-Dist: sphinx_bootstrap_theme>=0.4.12; extra == "docs"
Requires-Dist: sphinxcontrib-httpdomain>=1.5.0; extra == "docs"
Requires-Dist: sphinx_issues>=1.0.0; extra == "docs"
Requires-Dist: sphinx-rtd-theme>=0.4.2; extra == "docs"
Requires-Dist: nbsphinx>=0.3.5; extra == "docs"
Requires-Dist: photutils>=0.7; extra == "docs"
Requires-Dist: mpl-scatter-density>=0.4; extra == "docs"
Requires-Dist: jupyter_client>=5.2.3; extra == "docs"
Requires-Dist: ipykernel>5.0; extra == "docs"
Provides-Extra: web
Requires-Dist: blinker>=1.4; extra == "web"
Requires-Dist: Flask>=2; extra == "web"
Requires-Dist: werkzeug>=2; extra == "web"
Requires-Dist: Flask-FeatureFlags>=0.6; extra == "web"
Requires-Dist: Flask-Compress>=1.4; extra == "web"
Requires-Dist: Flask-Limiter>=0.9.4; extra == "web"
Requires-Dist: flask-profiler>=1.0.1; extra == "web"
Requires-Dist: Flask-Caching>=1.4.0; extra == "web"
Requires-Dist: Flask-Login>=0.4.1; extra == "web"
Requires-Dist: Flask-Cors>=3.0.8; extra == "web"
Requires-Dist: Flask-Session>=0.3.1; extra == "web"
Requires-Dist: redis>=3.3; extra == "web"
Requires-Dist: validators>=0.10.3; extra == "web"
Requires-Dist: intervals>=0.8.0; extra == "web"
Provides-Extra: db
Requires-Dist: pgpasslib>=1.1.0; extra == "db"
Requires-Dist: psycopg2>=2.6.2; extra == "db"
Requires-Dist: Flask-Login>=0.4.1; extra == "db"
Requires-Dist: sqlalchemy<2.0,>=1.3; extra == "db"
